Metadata-Version: 2.4
Name: pacu_snp
Version: 1.0.0
Summary: Workflow for whole genome sequencing based phylogeny of Illumina and ONT data.
Author-email: Bert Bogaerts <bioit@sciensano.be>
License: GPL-3.0-or-later
Project-URL: Homepage, https://github.com/BioinformaticsPlatformWIV-ISP/PACU/
Keywords: nanopore,illumina,sequencing,phylogeny
Classifier: Development Status :: 4 - Beta
Classifier: Intended Audience :: Science/Research
Classifier: Topic :: Scientific/Engineering :: Bio-Informatics
Classifier: License :: OSI Approved :: GNU General Public License v3 or later (GPLv3+)
Classifier: Programming Language :: Python :: 3
Requires-Python: >=3
License-File: LICENSE
Requires-Dist: PuLP==2.7.0
Requires-Dist: PyYAML
Requires-Dist: UpSetPlot>=0.8.0
Requires-Dist: beautifulsoup4
Requires-Dist: biopython
Requires-Dist: matplotlib>=3.7.1
Requires-Dist: numpy>=1.26.4
Requires-Dist: pandas>=2.1.0
Requires-Dist: pytest
Requires-Dist: pyvcf3>=1.0.3
Requires-Dist: snakemake==7.18.2
Requires-Dist: yattag
Dynamic: license-file
